sayswho/__init__.py
sayswho/constants.py
sayswho/helpers.py
sayswho/quote_finder.py
sayswho-0.1.4.dist-info/METADATA
sayswho-0.1.4.dist-info/WHEEL
sayswho-0.1.4.dist-info/RECORD
