Metadata-Version: 2.1
Name: sayswho
Version: 0.1.4
Summary: Quote identification, attribution and resolution.
Home-page: https://github.com/afriedman412/sayswho
License: MIT
Keywords: nlp,natural-language-processing,spacy
Author: Andy Friedman
Author-email: afriedman412@gmail.com
Requires-Python: >=3.9,<4.0
Classifier: License :: OSI Approved :: MIT License
Classifier: Programming Language :: Python :: 3
Classifier: Programming Language :: Python :: 3.9
Classifier: Programming Language :: Python :: 3.10
Classifier: Programming Language :: Python :: 3.11
Requires-Dist: pytest (>=7.4.0,<8.0.0)
Requires-Dist: rapidfuzz (>=3.1.1,<4.0.0)
Requires-Dist: regex (>=2023.6.3,<2024.0.0)
Requires-Dist: spacy (>=3.6.0,<4.0.0)
Project-URL: Repository, https://github.com/afriedman412/sayswho
